{
  "relationships_permanent_follow_requests": [
    {
      "title": "",
      "media_list_data": [
        
      ],
      "string_list_data": [
        {
          "href": "https://www.instagram.com/ta.p_._._",
          "value": "ta.p_._._",
          "timestamp": 1755840597
        }
      ]
    },
    {
      "title": "",
      "media_list_data": [
        
      ],
      "string_list_data": [
        {
          "href": "https://www.instagram.com/jpdp.tm1229",
          "value": "jpdp.tm1229",
          "timestamp": 1754747353
        }
      ]
    },
    {
      "title": "",
      "media_list_data": [
        
      ],
      "string_list_data": [
        {
          "href": "https://www.instagram.com/mana_yosshy",
          "value": "mana_yosshy",
          "timestamp": 1754318206
        }
      ]
    },
    {
      "title": "",
      "media_list_data": [
        
      ],
      "string_list_data": [
        {
          "href": "https://www.instagram.com/you_ratata",
          "value": "you_ratata",
          "timestamp": 1754317711
        }
      ]
    },
    {
      "title": "",
      "media_list_data": [
        
      ],
      "string_list_data": [
        {
          "href": "https://www.instagram.com/kbum_gym",
          "value": "kbum_gym",
          "timestamp": 1753549244
        }
      ]
    },
    {
      "title": "",
      "media_list_data": [
        
      ],
      "string_list_data": [
        {
          "href": "https://www.instagram.com/yuko_1559",
          "value": "yuko_1559",
          "timestamp": 1753158429
        }
      ]
    },
    {
      "title": "",
      "media_list_data": [
        
      ],
      "string_list_data": [
        {
          "href": "https://www.instagram.com/fleu_ris2",
          "value": "fleu_ris2",
          "timestamp": 1753062426
        }
      ]
    },
    {
      "title": "",
      "media_list_data": [
        
      ],
      "string_list_data": [
        {
          "href": "https://www.instagram.com/hina__625",
          "value": "hina__625",
          "timestamp": 1752910881
        }
      ]
    },
    {
      "title": "",
      "media_list_data": [
        
      ],
      "string_list_data": [
        {
          "href": "https://www.instagram.com/leeyaa683",
          "value": "leeyaa683",
          "timestamp": 1752302063
        }
      ]
    },
    {
      "title": "",
      "media_list_data": [
        
      ],
      "string_list_data": [
        {
          "href": "https://www.instagram.com/__s2xmy",
          "value": "__s2xmy",
          "timestamp": 1752302054
        }
      ]
    },
    {
      "title": "",
      "media_list_data": [
        
      ],
      "string_list_data": [
        {
          "href": "https://www.instagram.com/__saltoks",
          "value": "__saltoks",
          "timestamp": 1752245277
        }
      ]
    },
    {
      "title": "",
      "media_list_data": [
        
      ],
      "string_list_data": [
        {
          "href": "https://www.instagram.com/hkr_0122",
          "value": "hkr_0122",
          "timestamp": 1752245275
        }
      ]
    },
    {
      "title": "",
      "media_list_data": [
        
      ],
      "string_list_data": [
        {
          "href": "https://www.instagram.com/r.r_s022",
          "value": "r.r_s022",
          "timestamp": 1751258484
        }
      ]
    },
    {
      "title": "",
      "media_list_data": [
        
      ],
      "string_list_data": [
        {
          "href": "https://www.instagram.com/oii_ioi21",
          "value": "oii_ioi21",
          "timestamp": 1751011613
        }
      ]
    },
    {
      "title": "",
      "media_list_data": [
        
      ],
      "string_list_data": [
        {
          "href": "https://www.instagram.com/ema.__93",
          "value": "ema.__93",
          "timestamp": 1750427338
        }
      ]
    },
    {
      "title": "",
      "media_list_data": [
        
      ],
      "string_list_data": [
        {
          "href": "https://www.instagram.com/yuma_k0813",
          "value": "yuma_k0813",
          "timestamp": 1750248573
        }
      ]
    },
    {
      "title": "",
      "media_list_data": [
        
      ],
      "string_list_data": [
        {
          "href": "https://www.instagram.com/tai14_sea51",
          "value": "tai14_sea51",
          "timestamp": 1750155134
        }
      ]
    },
    {
      "title": "",
      "media_list_data": [
        
      ],
      "string_list_data": [
        {
          "href": "https://www.instagram.com/_chelsea.01",
          "value": "_chelsea.01",
          "timestamp": 1749849889
        }
      ]
    },
    {
      "title": "",
      "media_list_data": [
        
      ],
      "string_list_data": [
        {
          "href": "https://www.instagram.com/___sh1m1",
          "value": "___sh1m1",
          "timestamp": 1749462274
        }
      ]
    },
    {
      "title": "",
      "media_list_data": [
        
      ],
      "string_list_data": [
        {
          "href": "https://www.instagram.com/9val23e",
          "value": "9val23e",
          "timestamp": 1749462226
        }
      ]
    },
    {
      "title": "",
      "media_list_data": [
        
      ],
      "string_list_data": [
        {
          "href": "https://www.instagram.com/rikuse__taurus",
          "value": "rikuse__taurus",
          "timestamp": 1749300175
        }
      ]
    },
    {
      "title": "",
      "media_list_data": [
        
      ],
      "string_list_data": [
        {
          "href": "https://www.instagram.com/ayumu.y_19",
          "value": "ayumu.y_19",
          "timestamp": 1749271878
        }
      ]
    },
    {
      "title": "",
      "media_list_data": [
        
      ],
      "string_list_data": [
        {
          "href": "https://www.instagram.com/38ne_129",
          "value": "38ne_129",
          "timestamp": 1749114693
        }
      ]
    },
    {
      "title": "",
      "media_list_data": [
        
      ],
      "string_list_data": [
        {
          "href": "https://www.instagram.com/3island_h",
          "value": "3island_h",
          "timestamp": 1749114670
        }
      ]
    },
    {
      "title": "",
      "media_list_data": [
        
      ],
      "string_list_data": [
        {
          "href": "https://www.instagram.com/ayane_nk",
          "value": "ayane_nk",
          "timestamp": 1749114597
        }
      ]
    },
    {
      "title": "",
      "media_list_data": [
        
      ],
      "string_list_data": [
        {
          "href": "https://www.instagram.com/__osuz",
          "value": "__osuz",
          "timestamp": 1749114568
        }
      ]
    },
    {
      "title": "",
      "media_list_data": [
        
      ],
      "string_list_data": [
        {
          "href": "https://www.instagram.com/__ononon.918",
          "value": "__ononon.918",
          "timestamp": 1749114562
        }
      ]
    },
    {
      "title": "",
      "media_list_data": [
        
      ],
      "string_list_data": [
        {
          "href": "https://www.instagram.com/yuki_ki.0928",
          "value": "yuki_ki.0928",
          "timestamp": 1749114524
        }
      ]
    },
    {
      "title": "",
      "media_list_data": [
        
      ],
      "string_list_data": [
        {
          "href": "https://www.instagram.com/martijax",
          "value": "martijax",
          "timestamp": 1748881868
        }
      ]
    },
    {
      "title": "",
      "media_list_data": [
        
      ],
      "string_list_data": [
        {
          "href": "https://www.instagram.com/itslunq_8",
          "value": "itslunq_8",
          "timestamp": 1748177027
        }
      ]
    }
  ]
}